LICENSE
README.md
setup.py
pymadapi/__init__.py
pymadapi/__main__.py
pymadapi/errors.py
pymadapi/models.py
pymadapi.egg-info/PKG-INFO
pymadapi.egg-info/SOURCES.txt
pymadapi.egg-info/dependency_links.txt
pymadapi.egg-info/requires.txt
pymadapi.egg-info/top_level.txt
pymadapi/aio/__init__.py
pymadapi/aio/users.py
pymadapi/base/__init__.py
pymadapi/base/users.py