Metadata-Version: 2.1
Name: pymadapi
Version: 1.1.2
Summary: Python SDK for the MadAPI
Home-page: https://github.com/Team-MadBot/pyMadAPI
Author: MadCat9958
Author-email: abolvah8@gmail.com
License: MIT
Classifier: Programming Language :: Python :: 3
Classifier: Programming Language :: Python :: 3.6
Classifier: Programming Language :: Python :: 3.7
Classifier: Programming Language :: Python :: 3.8
Classifier: Programming Language :: Python :: 3.9
License-File: LICENSE
